jsonpeek/__init__.py
jsonpeek/cli.py
jsonpeek/core.py
jsonpeek-0.1.0.dist-info/LICENSE
jsonpeek-0.1.0.dist-info/METADATA
jsonpeek-0.1.0.dist-info/WHEEL
jsonpeek-0.1.0.dist-info/entry_points.txt
jsonpeek-0.1.0.dist-info/RECORD
